JDRros/__init__.py
JDRros/listenerBumper.py
JDRros/listenerCamera.py
JDRros/listenerLaser.py
JDRros/listenerPose3d.py
JDRros/listenerRgbd.py
JDRros/publisherMotors.py
JDRros/threadPublisher.py
jderobot_ros-1.0.2.dist-info/METADATA
jderobot_ros-1.0.2.dist-info/RECORD
jderobot_ros-1.0.2.dist-info/WHEEL
jderobot_ros-1.0.2.dist-info/top_level.txt
