Metadata-Version: 2.1
Name: jderobot-ros
Version: 1.0.2
Summary: ros utils package for jderobot projects
Home-page: https://github.com/JdeRobot/JdeRobot
Author: aitormf
Author-email: aitor.martinez.fernandez@gmail.com
License: UNKNOWN
Platform: UNKNOWN
Classifier: Programming Language :: Python
Classifier: License :: OSI Approved :: MIT License
Classifier: Operating System :: OS Independent
Requires-Dist: opencv-python
